plz_to_nuts/__init__.py
plz_to_nuts/__main__.py
plz_to_nuts/_version.py
plz_to_nuts/main.py
plz_to_nuts/nuts_data.py
plz2nuts-0.1.8.dist-info/METADATA
plz2nuts-0.1.8.dist-info/WHEEL
plz2nuts-0.1.8.dist-info/entry_points.txt
plz2nuts-0.1.8.dist-info/top_level.txt
plz2nuts-0.1.8.dist-info/RECORD
