Metadata-Version: 2.1
Name: plz2nuts
Version: 0.1.8
Summary: A Python package to convert German ZIP codes to NUTS IDs.
Author-email: Jonathan Sejdija <sejdija@fh-aachen.de>
License: GNU AFFERO GENERAL PUBLIC LICENSE
Project-URL: Documentation, https://github.com/NOWUM/plz-to-nuts
Requires-Python: >=3.7
Requires-Dist: pgeocode
